{
    "parent": "mobz:mob/archer",
    "display": {
        "icon": {
            "item": "mobz:archer2head"
        },
        "title": {
            "translate": "mobz.advancements.archer2.title"
        },
        "description": {
            "translate": "mobz.advancements.archer2.description"
        },
        "frame": "goal",
        "show_toast": true,
        "announce_to_chat": false,
        "hidden": false
    },
    "criteria": {
        "archering2": {
            "trigger": "minecraft:player_killed_entity",
            "conditions": {
                "entity": {
                    "type": "mobz:archer2_entity"
                }
            }
        }
    }
}